{
  "initialized": true,
  "seen_event_ids": [
    "sync-daily-2026-06-28",
    "debt-2023-04-01-twitter",
    "catalyst-2027-06-16-spacex",
    "spacex-edgar-0001628280-26-045763",
    "form4-year-2022",
    "filing-brief-0001628280-26-045763",
    "catalyst-2026-09-02-spacex",
    "debt-2027-09-02-spacex",
    "catalyst-2026-12-08-spacex",
    "sync-daily-2026-06-26",
    "spacex-edgar-0001628280-26-044955",
    "catalyst-2026-06-22-spacex",
    "alert-000162828026044955-8-K",
    "form4-year-2021",
    "sync-daily-2026-06-25",
    "alert-000162828026045763-8-K",
    "catalyst-2027-09-02-spacex",
    "spacex-edgar-0001628280-26-044489",
    "sync-daily-2026-06-27",
    "debt-2022-10-27-twitter",
    "filing-brief-0001628280-26-044955",
    "debt-2026-03-02-spacex",
    "debt-2026-02-02-spacex",
    "catalyst-2026-06-26-spacex-settlement",
    "catalyst-2026-08-20-spacex",
    "catalyst-2027-06-16-spacex-catalyst",
    "catalyst-2026-12-08-spacex-catalyst",
    "catalyst-2026-09-02-spacex-catalyst",
    "sync-daily-2026-06-23",
    "filing-brief-0001628280-26-044069",
    "sync-daily-2026-06-24",
    "debt-2026-06-15-spacex",
    "catalyst-2027-09-02-spacex-catalyst",
    "form4-year-2016",
    "catalyst-2026-06-22-spacex-catalyst",
    "form4-year-2010",
    "debt-2025-03-28-twitter",
    "catalyst-2026-08-20-spacex-catalyst",
    "form4-year-2026"
  ],
  "last_ingest": "2026-06-28T09:20:13Z",
  "last_synthesis": "2026-06-28T09:20:13Z",
  "event_count": 39
}